{"nodes":[{"name":"15","outputs":{},"isAcceptState":false,"node_id":"lvccpiz2ozf9ig6qfbr","draw_prop":"{\"x\":319,\"y\":52,\"radius\":45,\"fontSize\":20}"},{"name":"16","outputs":{},"isAcceptState":false,"node_id":"lvccpq7xvmxvgxb0s4o","draw_prop":"{\"x\":504,\"y\":52,\"radius\":45,\"fontSize\":20}"},{"name":"17","outputs":{},"isAcceptState":false,"node_id":"lvccq3po4kb0w0nor0r","draw_prop":"{\"x\":682,\"y\":52,\"radius\":45,\"fontSize\":20}"},{"name":"18","outputs":{},"isAcceptState":true,"node_id":"lvccq9ykatj2fl3z7vu","draw_prop":"{\"x\":860,\"y\":52,\"radius\":45,\"fontSize\":20}"},{"name":"19","outputs":{},"isAcceptState":true,"node_id":"lvccrsyf5hbsu9dl0sc","draw_prop":"{\"x\":319,\"y\":195,\"radius\":45,\"fontSize\":20}"},{"name":"20","outputs":{},"isAcceptState":false,"node_id":"lvccs25rw7z36aokhvj","draw_prop":"{\"x\":319,\"y\":316,\"radius\":45,\"fontSize\":20}"},{"name":"21","outputs":{},"isAcceptState":false,"node_id":"lvccsmzq6ajm5dce0fr","draw_prop":"{\"x\":494,\"y\":316,\"radius\":45,\"fontSize\":20}"},{"name":"22","outputs":{},"isAcceptState":false,"node_id":"lvccsvw5mo9l9mhid3s","draw_prop":"{\"x\":682,\"y\":316,\"radius\":45,\"fontSize\":20}"},{"name":"23","outputs":{},"isAcceptState":true,"node_id":"lvcct43miens1zyp1o","draw_prop":"{\"x\":860,\"y\":316,\"radius\":45,\"fontSize\":20}"},{"name":"24","outputs":{},"isAcceptState":false,"node_id":"lvccti7jjg4kjcm6udh","draw_prop":"{\"x\":319,\"y\":459,\"radius\":45,\"fontSize\":20}"},{"name":"25","outputs":{},"isAcceptState":false,"node_id":"lvccvcu2kofpffqqck","draw_prop":"{\"x\":494,\"y\":459,\"radius\":45,\"fontSize\":20}"},{"name":"26","outputs":{},"isAcceptState":true,"node_id":"lvccvittr5bt08vsg5","draw_prop":"{\"x\":682,\"y\":459,\"radius\":45,\"fontSize\":20}"},{"name":"27","outputs":{},"isAcceptState":true,"node_id":"lvccvwgmtyeoogwt5k","draw_prop":"{\"x\":151,\"y\":459,\"radius\":45,\"fontSize\":20}"},{"name":"27","outputs":{},"isAcceptState":false,"node_id":"lvccwgxm1tvszhbakndj","draw_prop":"{\"x\":319,\"y\":595,\"radius\":45,\"fontSize\":20}"},{"name":"28","outputs":{},"isAcceptState":false,"node_id":"lvccwlx81utc42yd819","draw_prop":"{\"x\":494,\"y\":595,\"radius\":45,\"fontSize\":20}"},{"name":"29","outputs":{},"isAcceptState":false,"node_id":"lvccwvpwj7nkas7hbn","draw_prop":"{\"x\":682,\"y\":595,\"radius\":45,\"fontSize\":20}"},{"name":"30","outputs":{},"isAcceptState":true,"node_id":"lvccxihckoqoh0bjv0s","draw_prop":"{\"x\":860,\"y\":595,\"radius\":45,\"fontSize\":20}"}],"links":[{"name":"or","source":"15","dest":"16","source_id":"lvccpiz2ozf9ig6qfbr","dest_id":"lvccpq7xvmxvgxb0s4o","link_id":"lvccpxbacczyo822gvs","draw_prop":"{\"type\":\"Link\",\"lineAngleAdjust\":0,\"parallelPart\":0.5,\"perpendicularPart\":0,\"fontSize\":20}"},{"name":"C","source":"16","dest":"17","source_id":"lvccpq7xvmxvgxb0s4o","dest_id":"lvccq3po4kb0w0nor0r","link_id":"lvccqfy7tdn8c5ah7tc","draw_prop":"{\"type\":\"Link\",\"lineAngleAdjust\":0,\"parallelPart\":0.5,\"perpendicularPart\":0,\"fontSize\":20}"},{"name":"E","source":"17","dest":"18","source_id":"lvccq3po4kb0w0nor0r","dest_id":"lvccq9ykatj2fl3z7vu","link_id":"lvccqj7cyrkw5jx4wpe","draw_prop":"{\"type\":\"Link\",\"lineAngleAdjust\":0,\"parallelPart\":0.5,\"perpendicularPart\":0,\"fontSize\":20}"},{"name":"id","source":"15","dest":"19","source_id":"lvccpiz2ozf9ig6qfbr","dest_id":"lvccrsyf5hbsu9dl0sc","link_id":"lvccryi5skhslm1dyl","draw_prop":"{\"type\":\"Link\",\"lineAngleAdjust\":0,\"parallelPart\":0.5,\"perpendicularPart\":0,\"fontSize\":20}"},{"name":"or","source":"20","dest":"21","source_id":"lvccs25rw7z36aokhvj","dest_id":"lvccsmzq6ajm5dce0fr","link_id":"lvccsprd5y6r9funaa","draw_prop":"{\"type\":\"Link\",\"lineAngleAdjust\":0,\"parallelPart\":0.5,\"perpendicularPart\":0,\"fontSize\":20}"},{"name":"C","source":"21","dest":"22","source_id":"lvccsmzq6ajm5dce0fr","dest_id":"lvccsvw5mo9l9mhid3s","link_id":"lvcct8kse2xq9dedlkg","draw_prop":"{\"type\":\"Link\",\"lineAngleAdjust\":0,\"parallelPart\":0.5,\"perpendicularPart\":0,\"fontSize\":20}"},{"name":"E'","source":"22","dest":"23","source_id":"lvccsvw5mo9l9mhid3s","dest_id":"lvcct43miens1zyp1o","link_id":"lvcct9qmcwf5063kej6","draw_prop":"{\"type\":\"Link\",\"lineAngleAdjust\":0,\"parallelPart\":0.5,\"perpendicularPart\":0,\"fontSize\":20}"},{"name":"not","source":"24","dest":"25","source_id":"lvccti7jjg4kjcm6udh","dest_id":"lvccvcu2kofpffqqck","link_id":"lvccvl5hdr2fht4v98","draw_prop":"{\"type\":\"Link\",\"lineAngleAdjust\":0,\"parallelPart\":0.5,\"perpendicularPart\":0,\"fontSize\":20}"},{"name":"C","source":"25","dest":"26","source_id":"lvccvcu2kofpffqqck","dest_id":"lvccvittr5bt08vsg5","link_id":"lvccvm237pk7u4njvw2","draw_prop":"{\"type\":\"Link\",\"lineAngleAdjust\":0,\"parallelPart\":0.5,\"perpendicularPart\":0,\"fontSize\":20}"},{"name":"num","source":"24","dest":"27","source_id":"lvccti7jjg4kjcm6udh","dest_id":"lvccvwgmtyeoogwt5k","link_id":"lvccwaueoun9dcxsjcc","draw_prop":"{\"type\":\"Link\",\"lineAngleAdjust\":0,\"parallelPart\":0.5,\"perpendicularPart\":0,\"fontSize\":20}"},{"name":"(","source":"24","dest":"27","source_id":"lvccti7jjg4kjcm6udh","dest_id":"lvccwgxm1tvszhbakndj","link_id":"lvccwjl98npzr3z6e8f","draw_prop":"{\"type\":\"Link\",\"lineAngleAdjust\":0,\"parallelPart\":0.5,\"perpendicularPart\":0,\"fontSize\":20}"},{"name":"A","source":"27","dest":"28","source_id":"lvccwgxm1tvszhbakndj","dest_id":"lvccwlx81utc42yd819","link_id":"lvccwuhdye9r636uuz","draw_prop":"{\"type\":\"Link\",\"lineAngleAdjust\":0,\"parallelPart\":0.5,\"perpendicularPart\":0,\"fontSize\":20}"},{"name":")","source":"28","dest":"29","source_id":"lvccwlx81utc42yd819","dest_id":"lvccwvpwj7nkas7hbn","link_id":"lvccx1ezalxmiz7wo64","draw_prop":"{\"type\":\"Link\",\"lineAngleAdjust\":0,\"parallelPart\":0.5,\"perpendicularPart\":0,\"fontSize\":20}"},{"name":"B","source":"29","dest":"30","source_id":"lvccwvpwj7nkas7hbn","dest_id":"lvccxihckoqoh0bjv0s","link_id":"lvccxndqy8c3699pnhg","draw_prop":"{\"type\":\"Link\",\"lineAngleAdjust\":0,\"parallelPart\":0.5,\"perpendicularPart\":0,\"fontSize\":20}"}]}